pyzdc/__init__.py
pyzdc/data/json/cities.json
pyzdc/data/json/columns_translated_english.json
pyzdc/data/json/states.json
pyzdc/extract/__init__.py
pyzdc/extract/get_raw.py
pyzdc/get_info/__init__.py
pyzdc/get_info/get_info.py
pyzdc/infer_schema/__init__.py
pyzdc/infer_schema/infer_schema.py
pyzdc/load/__init__.py
pyzdc/load/refresh_data.py
pyzdc/load/show_data.py
pyzdc/schemas/model_schema.py
pyzdc/schemas/model_schema_pydantic.py
pyzdc/transform/__init__.py
pyzdc/transform/transform_columns.py
pyzdc/transform/transform_db.py
pyzdc/utils/__init__.py
pyzdc/utils/config.py
pyzdc/utils/db_utils.py
pyzdc/utils/logger.py
pyzdc-0.6.1.dist-info/LICENSE
pyzdc-0.6.1.dist-info/METADATA
pyzdc-0.6.1.dist-info/WHEEL
pyzdc-0.6.1.dist-info/top_level.txt
pyzdc-0.6.1.dist-info/RECORD
