Metadata-Version: 2.2
Name: pyzdc
Version: 0.6.1
Summary: PyZDC is a Python package designed to facilitate the extraction, transformation, and analysis of epidemiological data related to Dengue, Zika, and Chikungunya.
Author-email: Gutto Franca <guttolaudie@gmail.com>
License: MIT License
Project-URL: Homepage, https://github.com/GuttoF/pyzdc
Project-URL: Issues, https://github.com/GuttoF/pyzdc/issues
Project-URL: Documentation, https://pyzdc.readthedocs.io/en/latest/
Classifier: Topic :: Education
Classifier: Natural Language :: English
Classifier: Development Status :: 3 - Alpha
Classifier: Programming Language :: Python :: 3.11
Classifier: Programming Language :: Python :: 3.12
Classifier: License :: Free for non-commercial use
Requires-Python: >=3.11
License-File: LICENSE
Requires-Dist: duckdb>=1.1.3
Requires-Dist: pandas>=2.2.3
Requires-Dist: pandera[io]>=0.22.1
Requires-Dist: pyarrow>=19.0.0
Requires-Dist: pysus>=0.15.0
Provides-Extra: doc
Requires-Dist: mkdocs>=1.6.1; extra == "doc"
Requires-Dist: mkdocs-material>=9.6.1; extra == "doc"
Requires-Dist: mkdocs-mermaid2-plugin>=1.2.1; extra == "doc"
Requires-Dist: mkdocstrings>=0.27.0; extra == "doc"
Requires-Dist: mkdocstrings-python>=1.13.0; extra == "doc"
